lykkellestatistics/__init__.py
lykkellestatistics/allstatisticseod.py
lykkellestatistics/getcompletelogreturneod.py
lykkellestatistics/getlastrollingmeaneod.py
lykkellestatistics/getlogreturneod.py
lykkellestatistics/getrollingmeaneod.py
lykkellestatistics-0.1.8.dist-info/LICENSE
lykkellestatistics-0.1.8.dist-info/METADATA
lykkellestatistics-0.1.8.dist-info/WHEEL
lykkellestatistics-0.1.8.dist-info/top_level.txt
lykkellestatistics-0.1.8.dist-info/RECORD
